{
  "document_name": "ORDEN 1493/2015, de 22 de mayo, de la Consejería de Educación, Juventud y \nDeporte, por la que se regula la evaluación y la promoción de los alumnos \ncon necesidad específica de apoyo educativo, que cursen segundo ciclo de \nEducación Infantil, Educación Primaria y Enseñanza Básica Obligatoria, así \ncomo la flexibilización de la duración de las enseñanzas de los alumnos con \naltas capacidades intelectuales en la Comunidad de Madrid.",
  "Publication Date": "LUNES 15 DE JUNIO DE 2015",
  "regulation_type": "Orden de la Comunidad de Madrid",
  "Law Identifier": "ORDEN 1493/2015",
  "Law title": "ORDEN 1493/2015, de 22 de mayo, de la Consejería de Educación, Juventud y Deporte, por la que se regula la evaluación y la promoción de los alumnos con necesidad específica de apoyo educativo, que cursen segundo ciclo de Educación Infantil, Educación Primaria y Enseñanza Básica Obligatoria, así como la flexi- bilización de la duración de las enseñanzas de los alumnos con altas capacida-\ndes intelectuales en la Comunidad de Madrid.",
  "url": "http://www.bocm.es/boletin/CM_Orden_BOCM/2015/06/15/BOCM-20150615-12.PDF",
  "publication_ref": "BOCM-20150615-12",
  "Structural Elements": {
    "Preambulo": {
      "Content": "La Ley Orgánica 2/2006, de 3 de mayo, de Educación, modificada por la Ley Orgáni- ca 8/2013, de 9 de diciembre, para la Mejora de la Calidad Educativa en su artículo 1 esta- blece que uno de los principios de la educación es la equidad que garantice la igualdad de oportunidades para el pleno desarrollo de la personalidad a través de la educación, la inclu- sión educativa, la igualdad de derechos y oportunidades que ayuden a superar cualquier dis- criminación y la accesibilidad universal a la educación, y que actúe como elemento com- pensador de las desigualdades personales, culturales, económicas y sociales, con especial atención a las que se deriven de cualquier tipo de discapacidad. Igualmente, recoge el prin- cipio de la flexibilidad para adecuar la educación a la diversidad de aptitudes, intereses, ex- pectativas y necesidades de los alumnos.\nAsimismo, en el artículo 71.2 de dicha norma indica que las Administraciones Educa- tivas asegurarán los recursos necesarios para que los alumnos y alumnas que requieran una atención educativa diferente a la ordinaria, por presentar necesidades educativas especiales, por dificultades específicas de aprendizaje, TDAH, por sus altas capacidades intelectuales, por haberse incorporado tarde al sistema educativo, o por condiciones personales o de his- toria escolar, puedan alcanzar el máximo desarrollo posible de sus capacidades personales y, en todo caso, los objetivos establecidos con carácter general para todo el alumnado.\nEntre los alumnos con necesidad específica de apoyo educativo, se incluyen los alum- nos que presentan necesidades educativas especiales definiéndolos, en el artículo 73, como aquellos que requieren, por un período de su escolarización o a lo largo de toda ella, deter- minados apoyos y atenciones educativas específicas derivadas de discapacidad o trastornos graves de conducta. De igual forma, el artículo 74.2 dispone que la identificación y valora- ción de las necesidades específicas de apoyo educativo de estos alumnos se realizarán lo más tempranamente posible, por personal con la debida cualificación y en los términos que determinen las Administraciones Educativas.\nPor otro lado, el artículo 76 establece que corresponde a las Administraciones Educa- tivas adoptar las medidas necesarias para identificar a los alumnos con altas capacidades in- telectuales y valorar de forma temprana sus necesidades. Asimismo, les corresponde adop- tar planes de actuación, así como programas de enriquecimiento curricular adecuados a dichas necesidades, que permitan a los alumnos desarrollar al máximo sus capacidades.\nLos Reales Decretos 1630/2006, de 29 de diciembre, y 126/2014, de 28 de febrero, por los que se establecen las enseñanzas mínimas del segundo ciclo de Educación Infantil y el currículo básico de la Educación Primaria, en sus artículos 8 y 9, respectivamente, indican que la intervención educativa debe contemplar como principio la diversidad de los alum- nos, y que las Administraciones Educativas, con el fin de facilitar la accesibilidad al currículo, establecerán las medidas más adecuadas para que las condiciones de realización de las evaluaciones se adapten a las necesidades de los alumnos con necesidad específica de apoyo educativo.\nComo desarrollo de los Reales Decretos anteriormente citados, la Comunidad de Madrid aprobó los Decretos 17/2008, de 6 de marzo, y 89/2014, de 24 de julio, del Conse- jo de Gobierno, por los que se establecen las enseñanzas de la Educación Infantil y el currículo de la Educación Primaria, y en sus artículos 2.3 y 17, respectivamente, recogen los principios generales de atención a la diversidad ya expuestos.\nAsimismo, la Orden 680/2009, de 19 de febrero, desarrolla para la Comunidad de Madrid la evaluación en Educación Infantil y los documentos de aplicación y la Or- den 3622/2014, de 3 de diciembre, de la Consejería de Educación, Juventud y Deporte de\nla Comunidad de Madrid, regula determinados aspectos de organización y funcionamien- to, así como la evaluación y los documentos de aplicación en la Educación Primaria.\nEs preciso regular y concretar el proceso de evaluación de los alumnos con necesidad específica de apoyo educativo que cursan segundo ciclo de Educación Infantil, Educación Primaria y Enseñanza Básica Obligatoria.\nEn el proceso de elaboración de esta Orden, ha emitido dictamen el Consejo Escolar de la Comunidad de Madrid, de acuerdo con el artículo 2.1.b) de la Ley 12/1999, de 29 de abril, de Creación del Consejo Escolar de la Comunidad de Madrid, modificado por el ar- tículo 29 de la Ley 9/2010, de 23 de diciembre. Asimismo, se ha tenido en cuenta el artícu- lo 41.d) de la Ley 1/1983, de 13 de diciembre, de Gobierno y Administración de la Comu- nidad de Madrid.\nLa Consejería de Educación, Juventud y Deporte es competente para regular los aspec- tos antedichos de acuerdo con las competencias a ella atribuidas por el Decreto 126/2012, de 25 de octubre, del Consejo de Gobierno, por el que se establece la estructura orgánica de la Consejería de Educación, Juventud y Deporte.\nEn su virtud, de conformidad con las atribuciones que me confiere el ordenamiento vigente,",
      "preambuloNumber": 0
    },
    "Titulo": [
      {
        "TitleNumber": 0,
        "TituloHeader": "",
        "content": "Capítulo I\nEvaluación y respuesta educativa a alumnos con necesidades educativas especiales y con altas capacidades intelectuales\nArtículo 1\nObjeto y ámbito\n1.La presente Orden tiene por objeto regular la evaluación de los alumnos con ne- cesidad específica de apoyo educativo. Principalmente, se refiere a aquellos que requieren, por un período de su escolarización o a lo largo de toda ella, determinados apoyos y aten- ciones educativas específicas derivadas de discapacidad así como a los alumnos con altas capacidades intelectuales.\n2.Esta Orden será de aplicación en los centros docentes, tanto públicos como priva- dos que, con la debida autorización, impartan segundo ciclo de Educación Infantil, Educa- ción Primaria y Enseñanza Básica Obligatoria, ya sea en centros ordinarios, centros de Edu- cación Especial o aulas de Educación Especial en centros ordinarios de la Comunidad de Madrid.\nArtículo 2\nCarácter de la evaluación\n1.La evaluación de los aprendizajes de los alumnos con necesidad específica de apo- yo educativo será continua y global y tendrá en cuenta su progreso en el conjunto de las áreas del currículo. En todo caso, tendrá carácter informativo, formativo y orientador del proceso de aprendizaje.\n2.La evaluación será realizada por el equipo docente, integrado por todos los maestros que atienden a cada alumno, coordinados por el maestro tutor del grupo al que pertenece.\nArtículo 3\nDetección temprana y atención educativa\n1.La identificación inicial de las necesidades específicas de apoyo educativo del alumno será realizada por el maestro tutor y por el equipo docente del mismo.\n2.Los centros arbitrarán las medidas organizativas y curriculares necesarias para ga- rantizar la adecuada atención educativa a las necesidades de estos alumnos tan pronto como estas sean detectadas.\n3.Los padres o tutores legales de los alumnos serán informados previamente a su aplicación, de las medidas organizativas y curriculares y de los recursos que se adopten para su atención.\nArtículo 4\nEvaluación psicopedagógica\n1.La evaluación psicopedagógica es el proceso de recogida, análisis y valoración de la información relevante referida al alumno y a su contexto familiar y escolar necesaria para determinar si un alumno tiene necesidades educativas especiales, si precisa adaptación curricular de acceso o significativa, de enriquecimiento, ampliación curricular o flexibili- zación del período de escolarización y para tomar las decisiones relativas a su escolariza- ción y promoción. Dicha evaluación psicopedagógica será revisada al final de cada etapa y, a petición del centro, al finalizar el tercer curso de Educación Primaria. Las conclusiones derivadas de la información obtenida se recogerán en un informe psicopedagógico cuyo modelo se establece en el Anexo I.\n2.El responsable de la realización de la evaluación psicopedagógica será, en todo caso, un profesor de la especialidad orientación educativa del equipo de orientación educa- tiva y psicopedagógica, el orientador del centro de educación especial o quien asuma las funciones de orientación educativa.\nArtículo 5\nAdaptaciones curriculares significativas de los alumnos con necesidades educativas especiales\n1.Las adaptaciones curriculares significativas se consideran una medida de carácter excepcional. Se realizarán, previa evaluación psicopedagógica, en el segundo ciclo de Edu- cación Infantil, en Educación Primaria y en Enseñanza Básica Obligatoria, e irán dirigidas a los alumnos que presentan necesidades educativas especiales.\n2.Una adaptación curricular será significativa cuando la modificación de los ele- mentos del currículo afecte al grado de consecución de los objetivos, los contenidos, los cri- terios de evaluación y, en su caso, los estándares de aprendizaje evaluables. Estas adapta- ciones se realizarán buscando el máximo desarrollo posible de las capacidades personales, y la consecución de los objetivos establecidos con carácter general para todos los alumnos.\n3.Cada maestro elaborará y desarrollará la adaptación curricular significativa co- rrespondiente al área o ámbito que imparta con el apoyo del resto de profesionales que pres- tan atención al alumno, teniendo en cuenta la evaluación psicopedagógica y las indicacio- nes del orientador del centro.\n4.El equipo de orientación educativa y psicopedagógica, el orientador del centro de educación especial o quien asuma las funciones de orientación educativa realizará o, en su caso, actualizará la evaluación psicopedagógica del alumno, con la participación de todos los profesionales implicados en la atención al mismo. Esta evaluación psicopedagógica re- cogerá la información referida al alumno y a su contexto familiar y escolar que resulte re- levante para ajustar la respuesta educativa a sus necesidades. Será imprescindible para de- terminar si un alumno tiene necesidades educativas especiales, para la toma de decisiones relativas a su escolarización y como base para la elaboración de adaptaciones curriculares significativas.\n5.Las familias colaborarán en el proceso de evaluación psicopedagógica de sus hi- jos y facilitarán los datos relevantes que les solicite el centro.\n6.El Documento Individual de Adaptación Curricular (DIAC) contendrá los datos de identificación del alumno, la adaptación significativa del currículo y las propuestas que se hayan realizado para facilitar su acceso a dicho currículo, las medidas de apoyo y los cri- terios de promoción. Dicho documento se adjuntará, en todo caso, al expediente académi- co del alumno.\nArtículo 6\nAdaptaciones curriculares de enriquecimiento y/o ampliación curricular para alumnos con altas capacidades intelectuales\n1.Para la atención a alumnos con altas capacidades se establecen las siguientes medidas:\na)El enriquecimiento curricular supone la realización de ajustes del currículo ordi- nario en algunos contenidos específicos de las áreas. Consiste en un aprendizaje interdisciplinar de mayor profundidad y extensión que el habitual.\nb)La ampliación curricular supone la modificación de los objetivos, contenidos, cri- terios de evaluación y estándares de aprendizaje evaluables en relación con el cur- so, o el ciclo en el caso de Educación Infantil, que al alumno con altas capacida-\ndes intelectuales le corresponde por edad. Estas adaptaciones implican la adquisición de objetivos y contenidos de cursos superiores.\n2.Este tipo de adaptaciones de ampliación y/o enriquecimiento deben llevarse a cabo cuando se valore que el alumno, en relación con el currículo que le corresponde por edad, presenta un rendimiento excepcional en un número determinado de áreas o un rendi- miento global excepcional y continuado.\n3.Las adaptaciones curriculares de ampliación y/o enriquecimiento de una o varias áreas del currículo se podrán realizar dentro del grupo de referencia del alumno o median- te la asistencia al curso inmediatamente superior al que realiza en ese momento.\nArtículo 7\nFlexibilización de la duración de las enseñanzas\nLa medida excepcional de flexibilización de la duración de las enseñanzas de Educa- ción Infantil y de Educación Primaria para los alumnos con altas capacidades intelectuales se atendrá a lo dispuesto en el capítulo II de esta Orden.\nArtículo 8\nEvaluación\n1.La evaluación del aprendizaje de los alumnos con necesidad específica de apoyo educativo se efectuará de acuerdo con lo dispuesto en los Decretos que establecen los cu- rrículos, así como en las normas que se concretan en sus respectivas Órdenes de evaluación en la Comunidad de Madrid.\n2.Los recursos materiales y personales, los tiempos y, en su caso, los apoyos nece- sarios para asegurar la correcta evaluación de los alumnos, se adecuarán teniendo en cuen- ta las adaptaciones curriculares significativas o de enriquecimiento y/o ampliación curricu- lar que se hubieran establecido en el centro.\n3.La evaluación de las áreas con adaptación curricular significativa o de enriqueci- miento y/o ampliación curricular tomará como referencia, según lo establecido en las co- rrespondientes órdenes de evaluación de cada etapa educativa, los elementos curriculares establecidos en su adaptación. Su elaboración será responsabilidad compartida del maestro que la imparte y de los maestros de apoyo.\n4.Los resultados de la evaluación de las áreas o ámbitos que hayan sido objeto de adaptación curricular significativa se expresarán en los mismos términos y utilizarán las mismas escalas que se establecen en la normativa que regula la evaluación de cada una de las etapas educativas excepto en la Enseñanza Básica Obligatoria, en la que las calificacio- nes tendrán carácter cualitativo, constará en ellas la referencia a la etapa o etapas a las que corresponden y se consignarán en los siguientes términos: C (conseguido), EP (en proceso) y NC (no conseguido).\n5.La información obtenida durante el proceso de evaluación servirá de referencia para introducir modificaciones en las medidas de atención adoptadas y para ajustarlas a las necesidades detectadas.\nArtículo 9\nConsignación en los documentos oficiales de evaluación de las adaptaciones curriculares significativas y medidas de enriquecimiento y/o ampliación curricular\n1.En el segundo ciclo de la Educación Infantil y en la Educación Primaria y en la Educación Básica Obligatoria la información relativa a las adaptaciones curriculares signi- ficativas y de enriquecimiento y ampliación curricular se consignará en los documentos ofi- ciales de evaluación tal como se recoge en el Anexo II.\n2.Los documentos oficiales en los que se consignarán las cuestiones relativas al pro- ceso de evaluación de los alumnos con necesidad específica de apoyo educativo serán los establecidos en la Orden 3622/2014, de 3 de diciembre, y la Orden 680/2009, de 19 de fe- brero, que regulan, respectivamente, la evaluación y los documentos de aplicación de la Educación Primaria y de la Educación Infantil en la Comunidad de Madrid y en las adap- taciones de dichos documentos que normativamente se establezcan para los alumnos que cursen Educación Básica Obligatoria.\nArtículo 10\nCoordinación, asesoramiento y supervisión\n1.La jefatura de estudios en los centros públicos, o quien asuma sus funciones en los centros privados, coordinará el desarrollo del proceso de organización de la atención a los alumnos con adaptaciones curriculares significativas y de las medidas de enriquecimiento y/o ampliación curricular de los alumnos con altas capacidades, con el visto bueno del Di- rector del centro.\n2.El Servicio de Inspección Educativa asesorará y supervisará dicho proceso.\nArtículo 11\nPromoción de los alumnos con necesidades educativas especiales e información a las familias\n1.La decisión de promoción se atendrá a lo que regula la normativa vigente y tomará como referente los elementos establecidos en las correspondientes adaptaciones curriculares.\n2.Los maestros tutores informarán por escrito a los padres o tutores legales de los alumnos, al menos trimestralmente, de los resultados de la evaluación de las áreas o ámbi- tos según las enseñanzas. En el caso del segundo ciclo de la Educación Infantil y de la Edu- cación Primaria, la información sobre los resultados de la evaluación del alumno incluirá el nivel al que corresponde su adaptación curricular, las medidas de apoyo adoptadas y, en su caso, la decisión de promoción.\nArtículo 12\nPermanencia de los alumnos con necesidades educativas especiales en el segundo ciclo de Educación Infantil\n1.La Dirección de Área Territorial correspondiente podrá autorizar, con carácter ex- cepcional, la permanencia de los alumnos con necesidades educativas especiales un año más en el segundo ciclo de Educación Infantil, siempre que no hayan agotado esta vía en el primer ciclo y se considere beneficioso para alcanzar los objetivos de la etapa así como para su aprendizaje y su integración social y educativa.\n2.El Director del centro en que se encuentre escolarizado el alumno solicitará la per- manencia de un año más en la etapa de Educación Infantil a la Dirección de Área Territo- rial en el último trimestre del curso escolar. La solicitud irá acompañada de la siguiente do- cumentación:\na)Informe psicopedagógico actualizado (Anexo I).\nb)Informe motivado del tutor y del equipo docente (Anexo III).\nc)Conformidad de los padres o tutores legales con la propuesta (Anexo IV).\n3.El titular de la Dirección de Área Territorial resolverá la autorización, previo in- forme del Servicio de Inspección Educativa (Anexo V), trasladando la decisión al centro docente antes de la finalización de las actividades lectivas del correspondiente curso esco- lar en el que se solicita.\nArtículo 13\nPermanencia de los alumnos con necesidades educativas especiales en la Educación Primaria\n1.Sin perjuicio de la permanencia durante un curso más en la etapa, la escolariza- ción de los alumnos con necesidades educativas especiales en Educación Primaria podrá prolongarse un año más siempre que ello favorezca su aprendizaje y su integración social y educativa.\n2.La decisión de prolongar la escolarización un segundo año más deberá tomarse de manera excepcional y siempre al finalizar la etapa. En consecuencia, esta decisión única- mente podrá adoptarse una vez que el alumno ya haya cursado sexto curso, ya haya perma- necido un año más en alguno de los cursos de la etapa, y siempre que esta medida favorez- ca su aprendizaje y su integración social y educativa, tal como se recoge en el apartado 1 de este artículo. La permanencia de un año más en Educación Infantil no impedirá la adop- ción de estas medidas.\n3.Los alumnos con necesidades educativas especiales no podrán repetir el mismo curso de la etapa una segunda vez. De manera excepcional, podrán repetir una segunda vez en sexto curso si no han repetido en cursos anteriores. La decisión será tomada por consen- so del equipo docente del alumno. Para ello se tendrá en cuenta sus informes de evaluación\npsicopedagógica y se tomará especialmente en consideración la información y el criterio del maestro tutor.\n4.El Director del centro en que se encuentre escolarizado el alumno solicitará la per- manencia de un segundo año más en la etapa de Educación Primaria a la que se refieren los apartados2y3 del presente artículo, a la Dirección de Área Territorial en el último trimes- tre del correspondiente año académico e informará de tal decisión a la familia del alumno.\n5.La solicitud deberá ir acompañada de la siguiente documentación:\na)Breve informe del equipo docente que atiende al alumno, exponiendo los motivos por los que la permanencia es beneficiosa para su aprendizaje y su integración.\nb)Justificante de haber informado a las familias.\n6.El titular de la Dirección de Área Territorial resolverá la autorización de perma- nencia en la etapa, previo informe del Servicio de Inspección Educativa (Anexo V), trasla- dando la decisión al centro docente antes de la finalización de las actividades lectivas del correspondiente curso escolar en el que se solicita.\nArtículo 14\nPermanencia de los alumnos con necesidades educativas especiales en la Enseñanza Básica Obligatoria\nLos alumnos escolarizados en centros de Educación Especial y en aulas de Educación Especial en centros ordinarios tendrán reconocidas automáticamente las mismas prórrogas de escolaridad que las establecidas en la enseñanza ordinaria. La permanencia un año más en el mismo ciclo o curso se realizará siempre a la finalización del mismo.\nCapítulo II\nMedidas de flexibilización para alumnos con altas capacidades intelectuales\nArtículo 15\nDefinición de flexibilización\n1.La flexibilización es una medida de carácter excepcional que consiste en la incor- poración de los alumnos con altas capacidades intelectuales a un curso superior al que por edad le correspondería.\n2.La flexibilización del período de escolarización podrá consistir tanto en la antici- pación del inicio de la Educación Primaria como en la reducción de la duración de esta.\nArtículo 16\nCriterios generales\n1.La medida de flexibilización para aquellos alumnos con altas capacidades intelec- tuales que tengan un potencial excepcional para el aprendizaje y un elevado rendimiento académico se tomará cuando las medidas educativas que el centro pueda adoptar se consi- deren insuficientes para atender adecuadamente al desarrollo de las capacidades de estos alumnos.\n2.Las decisiones académicas tomadas tras la correspondiente autorización para fle- xibilizar las etapas de Educación Infantil o de Educación Primaria estarán sujetas a un pro- ceso de evaluación. De dichas decisiones se informará a los padres o tutores legales de los alumnos.\n3.El maestro tutor y el equipo docente iniciarán las medidas de ampliación y/o en- riquecimiento curricular una vez detectadas las necesidades del alumno, de acuerdo con lo establecido en el artículo 6 de esta Orden, en tanto se toma la decisión de flexibilización tras la correspondiente evaluación psicopedagógica. La flexibilización se realizará, en su caso, el curso siguiente a aquel en que se haya llevado a cabo la evaluación psicopedagógi- ca del alumno.\nArtículo 17\nRequisitos\n1.El inicio de la Educación Primaria podrá anticiparse un año cuando en la evalua- ción psicopedagógica, acreditadas las altas capacidades intelectuales del alumno, se prevea\nque dicha medida es adecuada para su desarrollo intelectual, su equilibrio personal y su so- cialización y que globalmente tiene conseguidos los objetivos de la Educación Infantil.\n2.La Educación Primaria podrá reducirse hasta un máximo de dos cursos cuando en la evaluación psicopedagógica, acreditadas las altas capacidades intelectuales del alumno, se prevea que dicha medida es adecuada para su progreso intelectual y académico, su equi- librio personal y su socialización y que, globalmente, tiene adquiridos los objetivos del cur- so que le correspondería realizar. En el caso de que un alumno haya anticipado el inicio de la Educación Primaria, podrá reducir esta etapa una sola vez.\n3.La Consejería con competencia en materia de educación podrá, en casos excep- cionales, adoptar medidas de flexibilización sin tales limitaciones. Esta flexibilización in- corporará medidas y programas de atención específica.\nArtículo 18\nProcedimiento y plazos\n1.El procedimiento para solicitar la flexibilización del período de escolarización será el siguiente:\na)El maestro tutor, una vez detectadas las posibles altas capacidades del alumno in- formará a sus padres o tutores legales de esta circunstancia, a través de la direc- ción del centro y, con su conformidad, solicitará que se realice la evaluación psi- copedagógica del alumno. En este momento se iniciarán medidas de enriquecimiento y/o ampliación del currículo.\nb)La dirección del centro elevará a la Dirección de Área Territorial correspondiente, hasta el 15 de abril incluido de cada año académico, la solicitud de flexibilización, la cual incluirá, en todos los casos, la siguiente documentación:\n—Solicitud de autorización a los padres o tutores legales para realizar la evalua- ción psicopedagógica (Anexo VI).\n—El informe psicopedagógico actualizado, realizado por el equipo de orientación educativa y psicopedagógica. Este informe recogerá, de manera expresa, su propuesta favorable o desfavorable a la solicitud de flexibilización (Anexo I).\n—El informe del equipo docente coordinado por el maestro tutor del alumno. Este informe acreditará que el alumno tiene adquiridos los objetivos del cur- so que va a reducir en el caso de efectuarse la flexibilización (Anexo III).\n—La conformidad expresa de los padres o tutores legales del alumno, con la propuesta (Anexo IV).\n2.El Servicio de Inspección Educativa de la Dirección de Área Territorial corres- pondiente comprobará, una vez recibida la documentación, que se ajusta a lo establecido en esta Orden y emitirá el correspondiente informe (Anexo V).\n3.La Dirección de Área Territorial remitirá a la Dirección General con competencia en ordenación académica, en el plazo de diez días, la documentación mencionada en los apartados 1.b) y 2 de este artículo.\n4.La Dirección General con competencia en ordenación académica podrá requerir informes complementarios a la dirección del centro en el que el alumno esté escolarizado si la documentación del expediente está incompleta o no responde a lo regulado en esta Or- den. Estos informes complementarios se enviarán a dicha Dirección General, con copia a la Dirección de Área Territorial. En el caso de que no se reciban en el plazo que se haya indi- cado, se estimará desistida la solicitud de flexibilización.\n5.La Dirección General con competencia en ordenación académica resolverá antes de la finalización de las actividades lectivas, de manera que el alumno pueda anticipar o re- ducir el curso en el año académico siguiente a aquel en el que se ha iniciado el expediente de flexibilización.\nArtículo 19\nRecursos\nLa Dirección General competente en materia de ordenación académica comunicará la resolución a la Dirección de Área Territorial correspondiente para su traslado al Servicio de Inspección Educativa, al centro donde el alumno cursa sus estudios y a los interesados, quienes podrán interponer recurso de alzada contra dicha resolución, ante la Consejería con\ncompetencias en educación, en el plazo de un mes desde el día siguiente a la notificación de la misma.\nArtículo 20\nRegistro de la medida de flexibilización\nLa información relativa a la medida de flexibilización de la duración de las enseñanzas se consignará en los documentos oficiales de evaluación tal como se recoge en el Anexo II.\nArtículo 21\nSeguimiento\n1.El equipo docente y los equipos de orientación educativa y psicopedagógica serán los responsables de valorar la idoneidad de la medida adoptada. Esta se podrá anular cuan- do el alumno no alcance los objetivos propuestos, previo informe de evaluación psicopeda- gógica e informe razonado del equipo docente en el que se recogerá la nueva propuesta, que contará con el consentimiento escrito de los padres o tutores legales.\n2.El Servicio de Inspección Educativa garantizará, mediante informe, que se han respetado el procedimiento y los derechos del alumno.",
        "Capítulo": [
          {
            "CapítuloNumber": 1,
            "CapítuloHeader": "Evaluación y respuesta educativa a alumnos con necesidades educativas especiales y con altas capacidades intelectuales",
            "content": "Artículo 1\nObjeto y ámbito\n1.La presente Orden tiene por objeto regular la evaluación de los alumnos con ne- cesidad específica de apoyo educativo. Principalmente, se refiere a aquellos que requieren, por un período de su escolarización o a lo largo de toda ella, determinados apoyos y aten- ciones educativas específicas derivadas de discapacidad así como a los alumnos con altas capacidades intelectuales.\n2.Esta Orden será de aplicación en los centros docentes, tanto públicos como priva- dos que, con la debida autorización, impartan segundo ciclo de Educación Infantil, Educa- ción Primaria y Enseñanza Básica Obligatoria, ya sea en centros ordinarios, centros de Edu- cación Especial o aulas de Educación Especial en centros ordinarios de la Comunidad de Madrid.\nArtículo 2\nCarácter de la evaluación\n1.La evaluación de los aprendizajes de los alumnos con necesidad específica de apo- yo educativo será continua y global y tendrá en cuenta su progreso en el conjunto de las áreas del currículo. En todo caso, tendrá carácter informativo, formativo y orientador del proceso de aprendizaje.\n2.La evaluación será realizada por el equipo docente, integrado por todos los maestros que atienden a cada alumno, coordinados por el maestro tutor del grupo al que pertenece.\nArtículo 3\nDetección temprana y atención educativa\n1.La identificación inicial de las necesidades específicas de apoyo educativo del alumno será realizada por el maestro tutor y por el equipo docente del mismo.\n2.Los centros arbitrarán las medidas organizativas y curriculares necesarias para ga- rantizar la adecuada atención educativa a las necesidades de estos alumnos tan pronto como estas sean detectadas.\n3.Los padres o tutores legales de los alumnos serán informados previamente a su aplicación, de las medidas organizativas y curriculares y de los recursos que se adopten para su atención.\nArtículo 4\nEvaluación psicopedagógica\n1.La evaluación psicopedagógica es el proceso de recogida, análisis y valoración de la información relevante referida al alumno y a su contexto familiar y escolar necesaria para determinar si un alumno tiene necesidades educativas especiales, si precisa adaptación curricular de acceso o significativa, de enriquecimiento, ampliación curricular o flexibili- zación del período de escolarización y para tomar las decisiones relativas a su escolariza- ción y promoción. Dicha evaluación psicopedagógica será revisada al final de cada etapa y, a petición del centro, al finalizar el tercer curso de Educación Primaria. Las conclusiones derivadas de la información obtenida se recogerán en un informe psicopedagógico cuyo modelo se establece en el Anexo I.\n2.El responsable de la realización de la evaluación psicopedagógica será, en todo caso, un profesor de la especialidad orientación educativa del equipo de orientación educa- tiva y psicopedagógica, el orientador del centro de educación especial o quien asuma las funciones de orientación educativa.\nArtículo 5\nAdaptaciones curriculares significativas de los alumnos con necesidades educativas especiales\n1.Las adaptaciones curriculares significativas se consideran una medida de carácter excepcional. Se realizarán, previa evaluación psicopedagógica, en el segundo ciclo de Edu- cación Infantil, en Educación Primaria y en Enseñanza Básica Obligatoria, e irán dirigidas a los alumnos que presentan necesidades educativas especiales.\n2.Una adaptación curricular será significativa cuando la modificación de los ele- mentos del currículo afecte al grado de consecución de los objetivos, los contenidos, los cri- terios de evaluación y, en su caso, los estándares de aprendizaje evaluables. Estas adapta- ciones se realizarán buscando el máximo desarrollo posible de las capacidades personales, y la consecución de los objetivos establecidos con carácter general para todos los alumnos.\n3.Cada maestro elaborará y desarrollará la adaptación curricular significativa co- rrespondiente al área o ámbito que imparta con el apoyo del resto de profesionales que pres- tan atención al alumno, teniendo en cuenta la evaluación psicopedagógica y las indicacio- nes del orientador del centro.\n4.El equipo de orientación educativa y psicopedagógica, el orientador del centro de educación especial o quien asuma las funciones de orientación educativa realizará o, en su caso, actualizará la evaluación psicopedagógica del alumno, con la participación de todos los profesionales implicados en la atención al mismo. Esta evaluación psicopedagógica re- cogerá la información referida al alumno y a su contexto familiar y escolar que resulte re- levante para ajustar la respuesta educativa a sus necesidades. Será imprescindible para de- terminar si un alumno tiene necesidades educativas especiales, para la toma de decisiones relativas a su escolarización y como base para la elaboración de adaptaciones curriculares significativas.\n5.Las familias colaborarán en el proceso de evaluación psicopedagógica de sus hi- jos y facilitarán los datos relevantes que les solicite el centro.\n6.El Documento Individual de Adaptación Curricular (DIAC) contendrá los datos de identificación del alumno, la adaptación significativa del currículo y las propuestas que se hayan realizado para facilitar su acceso a dicho currículo, las medidas de apoyo y los cri- terios de promoción. Dicho documento se adjuntará, en todo caso, al expediente académi- co del alumno.\nArtículo 6\nAdaptaciones curriculares de enriquecimiento y/o ampliación curricular para alumnos con altas capacidades intelectuales\n1.Para la atención a alumnos con altas capacidades se establecen las siguientes medidas:\na)El enriquecimiento curricular supone la realización de ajustes del currículo ordi- nario en algunos contenidos específicos de las áreas. Consiste en un aprendizaje interdisciplinar de mayor profundidad y extensión que el habitual.\nb)La ampliación curricular supone la modificación de los objetivos, contenidos, cri- terios de evaluación y estándares de aprendizaje evaluables en relación con el cur- so, o el ciclo en el caso de Educación Infantil, que al alumno con altas capacida-\ndes intelectuales le corresponde por edad. Estas adaptaciones implican la adquisición de objetivos y contenidos de cursos superiores.\n2.Este tipo de adaptaciones de ampliación y/o enriquecimiento deben llevarse a cabo cuando se valore que el alumno, en relación con el currículo que le corresponde por edad, presenta un rendimiento excepcional en un número determinado de áreas o un rendi- miento global excepcional y continuado.\n3.Las adaptaciones curriculares de ampliación y/o enriquecimiento de una o varias áreas del currículo se podrán realizar dentro del grupo de referencia del alumno o median- te la asistencia al curso inmediatamente superior al que realiza en ese momento.\nArtículo 7\nFlexibilización de la duración de las enseñanzas\nLa medida excepcional de flexibilización de la duración de las enseñanzas de Educa- ción Infantil y de Educación Primaria para los alumnos con altas capacidades intelectuales se atendrá a lo dispuesto en el capítulo II de esta Orden.\nArtículo 8\nEvaluación\n1.La evaluación del aprendizaje de los alumnos con necesidad específica de apoyo educativo se efectuará de acuerdo con lo dispuesto en los Decretos que establecen los cu- rrículos, así como en las normas que se concretan en sus respectivas Órdenes de evaluación en la Comunidad de Madrid.\n2.Los recursos materiales y personales, los tiempos y, en su caso, los apoyos nece- sarios para asegurar la correcta evaluación de los alumnos, se adecuarán teniendo en cuen- ta las adaptaciones curriculares significativas o de enriquecimiento y/o ampliación curricu- lar que se hubieran establecido en el centro.\n3.La evaluación de las áreas con adaptación curricular significativa o de enriqueci- miento y/o ampliación curricular tomará como referencia, según lo establecido en las co- rrespondientes órdenes de evaluación de cada etapa educativa, los elementos curriculares establecidos en su adaptación. Su elaboración será responsabilidad compartida del maestro que la imparte y de los maestros de apoyo.\n4.Los resultados de la evaluación de las áreas o ámbitos que hayan sido objeto de adaptación curricular significativa se expresarán en los mismos términos y utilizarán las mismas escalas que se establecen en la normativa que regula la evaluación de cada una de las etapas educativas excepto en la Enseñanza Básica Obligatoria, en la que las calificacio- nes tendrán carácter cualitativo, constará en ellas la referencia a la etapa o etapas a las que corresponden y se consignarán en los siguientes términos: C (conseguido), EP (en proceso) y NC (no conseguido).\n5.La información obtenida durante el proceso de evaluación servirá de referencia para introducir modificaciones en las medidas de atención adoptadas y para ajustarlas a las necesidades detectadas.\nArtículo 9\nConsignación en los documentos oficiales de evaluación de las adaptaciones curriculares significativas y medidas de enriquecimiento y/o ampliación curricular\n1.En el segundo ciclo de la Educación Infantil y en la Educación Primaria y en la Educación Básica Obligatoria la información relativa a las adaptaciones curriculares signi- ficativas y de enriquecimiento y ampliación curricular se consignará en los documentos ofi- ciales de evaluación tal como se recoge en el Anexo II.\n2.Los documentos oficiales en los que se consignarán las cuestiones relativas al pro- ceso de evaluación de los alumnos con necesidad específica de apoyo educativo serán los establecidos en la Orden 3622/2014, de 3 de diciembre, y la Orden 680/2009, de 19 de fe- brero, que regulan, respectivamente, la evaluación y los documentos de aplicación de la Educación Primaria y de la Educación Infantil en la Comunidad de Madrid y en las adap- taciones de dichos documentos que normativamente se establezcan para los alumnos que cursen Educación Básica Obligatoria.\nArtículo 10\nCoordinación, asesoramiento y supervisión\n1.La jefatura de estudios en los centros públicos, o quien asuma sus funciones en los centros privados, coordinará el desarrollo del proceso de organización de la atención a los alumnos con adaptaciones curriculares significativas y de las medidas de enriquecimiento y/o ampliación curricular de los alumnos con altas capacidades, con el visto bueno del Di- rector del centro.\n2.El Servicio de Inspección Educativa asesorará y supervisará dicho proceso.\nArtículo 11\nPromoción de los alumnos con necesidades educativas especiales e información a las familias\n1.La decisión de promoción se atendrá a lo que regula la normativa vigente y tomará como referente los elementos establecidos en las correspondientes adaptaciones curriculares.\n2.Los maestros tutores informarán por escrito a los padres o tutores legales de los alumnos, al menos trimestralmente, de los resultados de la evaluación de las áreas o ámbi- tos según las enseñanzas. En el caso del segundo ciclo de la Educación Infantil y de la Edu- cación Primaria, la información sobre los resultados de la evaluación del alumno incluirá el nivel al que corresponde su adaptación curricular, las medidas de apoyo adoptadas y, en su caso, la decisión de promoción.\nArtículo 12\nPermanencia de los alumnos con necesidades educativas especiales en el segundo ciclo de Educación Infantil\n1.La Dirección de Área Territorial correspondiente podrá autorizar, con carácter ex- cepcional, la permanencia de los alumnos con necesidades educativas especiales un año más en el segundo ciclo de Educación Infantil, siempre que no hayan agotado esta vía en el primer ciclo y se considere beneficioso para alcanzar los objetivos de la etapa así como para su aprendizaje y su integración social y educativa.\n2.El Director del centro en que se encuentre escolarizado el alumno solicitará la per- manencia de un año más en la etapa de Educación Infantil a la Dirección de Área Territo- rial en el último trimestre del curso escolar. La solicitud irá acompañada de la siguiente do- cumentación:\na)Informe psicopedagógico actualizado (Anexo I).\nb)Informe motivado del tutor y del equipo docente (Anexo III).\nc)Conformidad de los padres o tutores legales con la propuesta (Anexo IV).\n3.El titular de la Dirección de Área Territorial resolverá la autorización, previo in- forme del Servicio de Inspección Educativa (Anexo V), trasladando la decisión al centro docente antes de la finalización de las actividades lectivas del correspondiente curso esco- lar en el que se solicita.\nArtículo 13\nPermanencia de los alumnos con necesidades educativas especiales en la Educación Primaria\n1.Sin perjuicio de la permanencia durante un curso más en la etapa, la escolariza- ción de los alumnos con necesidades educativas especiales en Educación Primaria podrá prolongarse un año más siempre que ello favorezca su aprendizaje y su integración social y educativa.\n2.La decisión de prolongar la escolarización un segundo año más deberá tomarse de manera excepcional y siempre al finalizar la etapa. En consecuencia, esta decisión única- mente podrá adoptarse una vez que el alumno ya haya cursado sexto curso, ya haya perma- necido un año más en alguno de los cursos de la etapa, y siempre que esta medida favorez- ca su aprendizaje y su integración social y educativa, tal como se recoge en el apartado 1 de este artículo. La permanencia de un año más en Educación Infantil no impedirá la adop- ción de estas medidas.\n3.Los alumnos con necesidades educativas especiales no podrán repetir el mismo curso de la etapa una segunda vez. De manera excepcional, podrán repetir una segunda vez en sexto curso si no han repetido en cursos anteriores. La decisión será tomada por consen- so del equipo docente del alumno. Para ello se tendrá en cuenta sus informes de evaluación\npsicopedagógica y se tomará especialmente en consideración la información y el criterio del maestro tutor.\n4.El Director del centro en que se encuentre escolarizado el alumno solicitará la per- manencia de un segundo año más en la etapa de Educación Primaria a la que se refieren los apartados2y3 del presente artículo, a la Dirección de Área Territorial en el último trimes- tre del correspondiente año académico e informará de tal decisión a la familia del alumno.\n5.La solicitud deberá ir acompañada de la siguiente documentación:\na)Breve informe del equipo docente que atiende al alumno, exponiendo los motivos por los que la permanencia es beneficiosa para su aprendizaje y su integración.\nb)Justificante de haber informado a las familias.\n6.El titular de la Dirección de Área Territorial resolverá la autorización de perma- nencia en la etapa, previo informe del Servicio de Inspección Educativa (Anexo V), trasla- dando la decisión al centro docente antes de la finalización de las actividades lectivas del correspondiente curso escolar en el que se solicita.\nArtículo 14\nPermanencia de los alumnos con necesidades educativas especiales en la Enseñanza Básica Obligatoria\nLos alumnos escolarizados en centros de Educación Especial y en aulas de Educación Especial en centros ordinarios tendrán reconocidas automáticamente las mismas prórrogas de escolaridad que las establecidas en la enseñanza ordinaria. La permanencia un año más en el mismo ciclo o curso se realizará siempre a la finalización del mismo.",
            "Sección": [
              {
                "SecciónNumber": 0,
                "SecciónHeader": "",
                "content": "",
                "articles": [
                  {
                    "ArtículoNumber": 1,
                    "ArtículoHeader": "Artículo 1",
                    "content": "1.La presente Orden tiene por objeto regular la evaluación de los alumnos con ne- cesidad específica de apoyo educativo. Principalmente, se refiere a aquellos que requieren, por un período de su escolarización o a lo largo de toda ella, determinados apoyos y aten- ciones educativas específicas derivadas de discapacidad así como a los alumnos con altas capacidades intelectuales.\n2.Esta Orden será de aplicación en los centros docentes, tanto públicos como priva- dos que, con la debida autorización, impartan segundo ciclo de Educación Infantil, Educa- ción Primaria y Enseñanza Básica Obligatoria, ya sea en centros ordinarios, centros de Edu- cación Especial o aulas de Educación Especial en centros ordinarios de la Comunidad de Madrid.",
                    "subtitle": "Objeto y ámbito"
                  },
                  {
                    "ArtículoNumber": 2,
                    "ArtículoHeader": "Artículo 2",
                    "content": "1.La evaluación de los aprendizajes de los alumnos con necesidad específica de apo- yo educativo será continua y global y tendrá en cuenta su progreso en el conjunto de las áreas del currículo. En todo caso, tendrá carácter informativo, formativo y orientador del proceso de aprendizaje.\n2.La evaluación será realizada por el equipo docente, integrado por todos los maestros que atienden a cada alumno, coordinados por el maestro tutor del grupo al que pertenece.",
                    "subtitle": "Carácter de la evaluación"
                  },
                  {
                    "ArtículoNumber": 3,
                    "ArtículoHeader": "Artículo 3",
                    "content": "1.La identificación inicial de las necesidades específicas de apoyo educativo del alumno será realizada por el maestro tutor y por el equipo docente del mismo.\n2.Los centros arbitrarán las medidas organizativas y curriculares necesarias para ga- rantizar la adecuada atención educativa a las necesidades de estos alumnos tan pronto como estas sean detectadas.\n3.Los padres o tutores legales de los alumnos serán informados previamente a su aplicación, de las medidas organizativas y curriculares y de los recursos que se adopten para su atención.",
                    "subtitle": "Detección temprana y atención educativa"
                  },
                  {
                    "ArtículoNumber": 4,
                    "ArtículoHeader": "Artículo 4",
                    "content": "1.La evaluación psicopedagógica es el proceso de recogida, análisis y valoración de la información relevante referida al alumno y a su contexto familiar y escolar necesaria para determinar si un alumno tiene necesidades educativas especiales, si precisa adaptación curricular de acceso o significativa, de enriquecimiento, ampliación curricular o flexibili- zación del período de escolarización y para tomar las decisiones relativas a su escolariza- ción y promoción. Dicha evaluación psicopedagógica será revisada al final de cada etapa y, a petición del centro, al finalizar el tercer curso de Educación Primaria. Las conclusiones derivadas de la información obtenida se recogerán en un informe psicopedagógico cuyo modelo se establece en el Anexo I.\n2.El responsable de la realización de la evaluación psicopedagógica será, en todo caso, un profesor de la especialidad orientación educativa del equipo de orientación educa- tiva y psicopedagógica, el orientador del centro de educación especial o quien asuma las funciones de orientación educativa.",
                    "subtitle": "Evaluación psicopedagógica"
                  },
                  {
                    "ArtículoNumber": 5,
                    "ArtículoHeader": "Artículo 5",
                    "content": "1.Las adaptaciones curriculares significativas se consideran una medida de carácter excepcional. Se realizarán, previa evaluación psicopedagógica, en el segundo ciclo de Edu- cación Infantil, en Educación Primaria y en Enseñanza Básica Obligatoria, e irán dirigidas a los alumnos que presentan necesidades educativas especiales.\n2.Una adaptación curricular será significativa cuando la modificación de los ele- mentos del currículo afecte al grado de consecución de los objetivos, los contenidos, los cri- terios de evaluación y, en su caso, los estándares de aprendizaje evaluables. Estas adapta- ciones se realizarán buscando el máximo desarrollo posible de las capacidades personales, y la consecución de los objetivos establecidos con carácter general para todos los alumnos.\n3.Cada maestro elaborará y desarrollará la adaptación curricular significativa co- rrespondiente al área o ámbito que imparta con el apoyo del resto de profesionales que pres- tan atención al alumno, teniendo en cuenta la evaluación psicopedagógica y las indicacio- nes del orientador del centro.\n4.El equipo de orientación educativa y psicopedagógica, el orientador del centro de educación especial o quien asuma las funciones de orientación educativa realizará o, en su caso, actualizará la evaluación psicopedagógica del alumno, con la participación de todos los profesionales implicados en la atención al mismo. Esta evaluación psicopedagógica re- cogerá la información referida al alumno y a su contexto familiar y escolar que resulte re- levante para ajustar la respuesta educativa a sus necesidades. Será imprescindible para de- terminar si un alumno tiene necesidades educativas especiales, para la toma de decisiones relativas a su escolarización y como base para la elaboración de adaptaciones curriculares significativas.\n5.Las familias colaborarán en el proceso de evaluación psicopedagógica de sus hi- jos y facilitarán los datos relevantes que les solicite el centro.\n6.El Documento Individual de Adaptación Curricular (DIAC) contendrá los datos de identificación del alumno, la adaptación significativa del currículo y las propuestas que se hayan realizado para facilitar su acceso a dicho currículo, las medidas de apoyo y los cri- terios de promoción. Dicho documento se adjuntará, en todo caso, al expediente académi- co del alumno.",
                    "subtitle": "Adaptaciones curriculares significativas de los alumnos con necesidades educativas especiales"
                  },
                  {
                    "ArtículoNumber": 6,
                    "ArtículoHeader": "Artículo 6",
                    "content": "1.Para la atención a alumnos con altas capacidades se establecen las siguientes medidas:\na)El enriquecimiento curricular supone la realización de ajustes del currículo ordi- nario en algunos contenidos específicos de las áreas. Consiste en un aprendizaje interdisciplinar de mayor profundidad y extensión que el habitual.\nb)La ampliación curricular supone la modificación de los objetivos, contenidos, cri- terios de evaluación y estándares de aprendizaje evaluables en relación con el cur- so, o el ciclo en el caso de Educación Infantil, que al alumno con altas capacida-\ndes intelectuales le corresponde por edad. Estas adaptaciones implican la adquisición de objetivos y contenidos de cursos superiores.\n2.Este tipo de adaptaciones de ampliación y/o enriquecimiento deben llevarse a cabo cuando se valore que el alumno, en relación con el currículo que le corresponde por edad, presenta un rendimiento excepcional en un número determinado de áreas o un rendi- miento global excepcional y continuado.\n3.Las adaptaciones curriculares de ampliación y/o enriquecimiento de una o varias áreas del currículo se podrán realizar dentro del grupo de referencia del alumno o median- te la asistencia al curso inmediatamente superior al que realiza en ese momento.",
                    "subtitle": "Adaptaciones curriculares de enriquecimiento y/o ampliación curricular para alumnos con altas capacidades intelectuales"
                  },
                  {
                    "ArtículoNumber": 7,
                    "ArtículoHeader": "Artículo 7",
                    "content": "La medida excepcional de flexibilización de la duración de las enseñanzas de Educa- ción Infantil y de Educación Primaria para los alumnos con altas capacidades intelectuales se atendrá a lo dispuesto en el capítulo II de esta Orden.",
                    "subtitle": "Flexibilización de la duración de las enseñanzas"
                  },
                  {
                    "ArtículoNumber": 8,
                    "ArtículoHeader": "Artículo 8",
                    "content": "1.La evaluación del aprendizaje de los alumnos con necesidad específica de apoyo educativo se efectuará de acuerdo con lo dispuesto en los Decretos que establecen los cu- rrículos, así como en las normas que se concretan en sus respectivas Órdenes de evaluación en la Comunidad de Madrid.\n2.Los recursos materiales y personales, los tiempos y, en su caso, los apoyos nece- sarios para asegurar la correcta evaluación de los alumnos, se adecuarán teniendo en cuen- ta las adaptaciones curriculares significativas o de enriquecimiento y/o ampliación curricu- lar que se hubieran establecido en el centro.\n3.La evaluación de las áreas con adaptación curricular significativa o de enriqueci- miento y/o ampliación curricular tomará como referencia, según lo establecido en las co- rrespondientes órdenes de evaluación de cada etapa educativa, los elementos curriculares establecidos en su adaptación. Su elaboración será responsabilidad compartida del maestro que la imparte y de los maestros de apoyo.\n4.Los resultados de la evaluación de las áreas o ámbitos que hayan sido objeto de adaptación curricular significativa se expresarán en los mismos términos y utilizarán las mismas escalas que se establecen en la normativa que regula la evaluación de cada una de las etapas educativas excepto en la Enseñanza Básica Obligatoria, en la que las calificacio- nes tendrán carácter cualitativo, constará en ellas la referencia a la etapa o etapas a las que corresponden y se consignarán en los siguientes términos: C (conseguido), EP (en proceso) y NC (no conseguido).\n5.La información obtenida durante el proceso de evaluación servirá de referencia para introducir modificaciones en las medidas de atención adoptadas y para ajustarlas a las necesidades detectadas.",
                    "subtitle": "Evaluación"
                  },
                  {
                    "ArtículoNumber": 9,
                    "ArtículoHeader": "Artículo 9",
                    "content": "1.En el segundo ciclo de la Educación Infantil y en la Educación Primaria y en la Educación Básica Obligatoria la información relativa a las adaptaciones curriculares signi- ficativas y de enriquecimiento y ampliación curricular se consignará en los documentos ofi- ciales de evaluación tal como se recoge en el Anexo II.\n2.Los documentos oficiales en los que se consignarán las cuestiones relativas al pro- ceso de evaluación de los alumnos con necesidad específica de apoyo educativo serán los establecidos en la Orden 3622/2014, de 3 de diciembre, y la Orden 680/2009, de 19 de fe- brero, que regulan, respectivamente, la evaluación y los documentos de aplicación de la Educación Primaria y de la Educación Infantil en la Comunidad de Madrid y en las adap- taciones de dichos documentos que normativamente se establezcan para los alumnos que cursen Educación Básica Obligatoria.",
                    "subtitle": "Consignación en los documentos oficiales de evaluación de las adaptaciones curriculares significativas y medidas de enriquecimiento y/o ampliación curricular"
                  },
                  {
                    "ArtículoNumber": 10,
                    "ArtículoHeader": "Artículo 10",
                    "content": "1.La jefatura de estudios en los centros públicos, o quien asuma sus funciones en los centros privados, coordinará el desarrollo del proceso de organización de la atención a los alumnos con adaptaciones curriculares significativas y de las medidas de enriquecimiento y/o ampliación curricular de los alumnos con altas capacidades, con el visto bueno del Di- rector del centro.\n2.El Servicio de Inspección Educativa asesorará y supervisará dicho proceso.",
                    "subtitle": "Coordinación, asesoramiento y supervisión"
                  },
                  {
                    "ArtículoNumber": 11,
                    "ArtículoHeader": "Artículo 11",
                    "content": "1.La decisión de promoción se atendrá a lo que regula la normativa vigente y tomará como referente los elementos establecidos en las correspondientes adaptaciones curriculares.\n2.Los maestros tutores informarán por escrito a los padres o tutores legales de los alumnos, al menos trimestralmente, de los resultados de la evaluación de las áreas o ámbi- tos según las enseñanzas. En el caso del segundo ciclo de la Educación Infantil y de la Edu- cación Primaria, la información sobre los resultados de la evaluación del alumno incluirá el nivel al que corresponde su adaptación curricular, las medidas de apoyo adoptadas y, en su caso, la decisión de promoción.",
                    "subtitle": "Promoción de los alumnos con necesidades educativas especiales e información a las familias"
                  },
                  {
                    "ArtículoNumber": 12,
                    "ArtículoHeader": "Artículo 12",
                    "content": "1.La Dirección de Área Territorial correspondiente podrá autorizar, con carácter ex- cepcional, la permanencia de los alumnos con necesidades educativas especiales un año más en el segundo ciclo de Educación Infantil, siempre que no hayan agotado esta vía en el primer ciclo y se considere beneficioso para alcanzar los objetivos de la etapa así como para su aprendizaje y su integración social y educativa.\n2.El Director del centro en que se encuentre escolarizado el alumno solicitará la per- manencia de un año más en la etapa de Educación Infantil a la Dirección de Área Territo- rial en el último trimestre del curso escolar. La solicitud irá acompañada de la siguiente do- cumentación:\na)Informe psicopedagógico actualizado (Anexo I).\nb)Informe motivado del tutor y del equipo docente (Anexo III).\nc)Conformidad de los padres o tutores legales con la propuesta (Anexo IV).\n3.El titular de la Dirección de Área Territorial resolverá la autorización, previo in- forme del Servicio de Inspección Educativa (Anexo V), trasladando la decisión al centro docente antes de la finalización de las actividades lectivas del correspondiente curso esco- lar en el que se solicita.",
                    "subtitle": "Permanencia de los alumnos con necesidades educativas especiales en el segundo ciclo de Educación Infantil"
                  },
                  {
                    "ArtículoNumber": 13,
                    "ArtículoHeader": "Artículo 13",
                    "content": "1.Sin perjuicio de la permanencia durante un curso más en la etapa, la escolariza- ción de los alumnos con necesidades educativas especiales en Educación Primaria podrá prolongarse un año más siempre que ello favorezca su aprendizaje y su integración social y educativa.\n2.La decisión de prolongar la escolarización un segundo año más deberá tomarse de manera excepcional y siempre al finalizar la etapa. En consecuencia, esta decisión única- mente podrá adoptarse una vez que el alumno ya haya cursado sexto curso, ya haya perma- necido un año más en alguno de los cursos de la etapa, y siempre que esta medida favorez- ca su aprendizaje y su integración social y educativa, tal como se recoge en el apartado 1 de este artículo. La permanencia de un año más en Educación Infantil no impedirá la adop- ción de estas medidas.\n3.Los alumnos con necesidades educativas especiales no podrán repetir el mismo curso de la etapa una segunda vez. De manera excepcional, podrán repetir una segunda vez en sexto curso si no han repetido en cursos anteriores. La decisión será tomada por consen- so del equipo docente del alumno. Para ello se tendrá en cuenta sus informes de evaluación\npsicopedagógica y se tomará especialmente en consideración la información y el criterio del maestro tutor.\n4.El Director del centro en que se encuentre escolarizado el alumno solicitará la per- manencia de un segundo año más en la etapa de Educación Primaria a la que se refieren los apartados2y3 del presente artículo, a la Dirección de Área Territorial en el último trimes- tre del correspondiente año académico e informará de tal decisión a la familia del alumno.\n5.La solicitud deberá ir acompañada de la siguiente documentación:\na)Breve informe del equipo docente que atiende al alumno, exponiendo los motivos por los que la permanencia es beneficiosa para su aprendizaje y su integración.\nb)Justificante de haber informado a las familias.\n6.El titular de la Dirección de Área Territorial resolverá la autorización de perma- nencia en la etapa, previo informe del Servicio de Inspección Educativa (Anexo V), trasla- dando la decisión al centro docente antes de la finalización de las actividades lectivas del correspondiente curso escolar en el que se solicita.",
                    "subtitle": "Permanencia de los alumnos con necesidades educativas especiales en la Educación Primaria"
                  },
                  {
                    "ArtículoNumber": 14,
                    "ArtículoHeader": "Artículo 14",
                    "content": "Los alumnos escolarizados en centros de Educación Especial y en aulas de Educación Especial en centros ordinarios tendrán reconocidas automáticamente las mismas prórrogas de escolaridad que las establecidas en la enseñanza ordinaria. La permanencia un año más en el mismo ciclo o curso se realizará siempre a la finalización del mismo.",
                    "subtitle": "Permanencia de los alumnos con necesidades educativas especiales en la Enseñanza Básica Obligatoria"
                  }
                ]
              }
            ]
          },
          {
            "CapítuloNumber": 2,
            "CapítuloHeader": "Medidas de flexibilización para alumnos con altas capacidades intelectuales",
            "content": "Artículo 15\nDefinición de flexibilización\n1.La flexibilización es una medida de carácter excepcional que consiste en la incor- poración de los alumnos con altas capacidades intelectuales a un curso superior al que por edad le correspondería.\n2.La flexibilización del período de escolarización podrá consistir tanto en la antici- pación del inicio de la Educación Primaria como en la reducción de la duración de esta.\nArtículo 16\nCriterios generales\n1.La medida de flexibilización para aquellos alumnos con altas capacidades intelec- tuales que tengan un potencial excepcional para el aprendizaje y un elevado rendimiento académico se tomará cuando las medidas educativas que el centro pueda adoptar se consi- deren insuficientes para atender adecuadamente al desarrollo de las capacidades de estos alumnos.\n2.Las decisiones académicas tomadas tras la correspondiente autorización para fle- xibilizar las etapas de Educación Infantil o de Educación Primaria estarán sujetas a un pro- ceso de evaluación. De dichas decisiones se informará a los padres o tutores legales de los alumnos.\n3.El maestro tutor y el equipo docente iniciarán las medidas de ampliación y/o en- riquecimiento curricular una vez detectadas las necesidades del alumno, de acuerdo con lo establecido en el artículo 6 de esta Orden, en tanto se toma la decisión de flexibilización tras la correspondiente evaluación psicopedagógica. La flexibilización se realizará, en su caso, el curso siguiente a aquel en que se haya llevado a cabo la evaluación psicopedagógi- ca del alumno.\nArtículo 17\nRequisitos\n1.El inicio de la Educación Primaria podrá anticiparse un año cuando en la evalua- ción psicopedagógica, acreditadas las altas capacidades intelectuales del alumno, se prevea\nque dicha medida es adecuada para su desarrollo intelectual, su equilibrio personal y su so- cialización y que globalmente tiene conseguidos los objetivos de la Educación Infantil.\n2.La Educación Primaria podrá reducirse hasta un máximo de dos cursos cuando en la evaluación psicopedagógica, acreditadas las altas capacidades intelectuales del alumno, se prevea que dicha medida es adecuada para su progreso intelectual y académico, su equi- librio personal y su socialización y que, globalmente, tiene adquiridos los objetivos del cur- so que le correspondería realizar. En el caso de que un alumno haya anticipado el inicio de la Educación Primaria, podrá reducir esta etapa una sola vez.\n3.La Consejería con competencia en materia de educación podrá, en casos excep- cionales, adoptar medidas de flexibilización sin tales limitaciones. Esta flexibilización in- corporará medidas y programas de atención específica.\nArtículo 18\nProcedimiento y plazos\n1.El procedimiento para solicitar la flexibilización del período de escolarización será el siguiente:\na)El maestro tutor, una vez detectadas las posibles altas capacidades del alumno in- formará a sus padres o tutores legales de esta circunstancia, a través de la direc- ción del centro y, con su conformidad, solicitará que se realice la evaluación psi- copedagógica del alumno. En este momento se iniciarán medidas de enriquecimiento y/o ampliación del currículo.\nb)La dirección del centro elevará a la Dirección de Área Territorial correspondiente, hasta el 15 de abril incluido de cada año académico, la solicitud de flexibilización, la cual incluirá, en todos los casos, la siguiente documentación:\n—Solicitud de autorización a los padres o tutores legales para realizar la evalua- ción psicopedagógica (Anexo VI).\n—El informe psicopedagógico actualizado, realizado por el equipo de orientación educativa y psicopedagógica. Este informe recogerá, de manera expresa, su propuesta favorable o desfavorable a la solicitud de flexibilización (Anexo I).\n—El informe del equipo docente coordinado por el maestro tutor del alumno. Este informe acreditará que el alumno tiene adquiridos los objetivos del cur- so que va a reducir en el caso de efectuarse la flexibilización (Anexo III).\n—La conformidad expresa de los padres o tutores legales del alumno, con la propuesta (Anexo IV).\n2.El Servicio de Inspección Educativa de la Dirección de Área Territorial corres- pondiente comprobará, una vez recibida la documentación, que se ajusta a lo establecido en esta Orden y emitirá el correspondiente informe (Anexo V).\n3.La Dirección de Área Territorial remitirá a la Dirección General con competencia en ordenación académica, en el plazo de diez días, la documentación mencionada en los apartados 1.b) y 2 de este artículo.\n4.La Dirección General con competencia en ordenación académica podrá requerir informes complementarios a la dirección del centro en el que el alumno esté escolarizado si la documentación del expediente está incompleta o no responde a lo regulado en esta Or- den. Estos informes complementarios se enviarán a dicha Dirección General, con copia a la Dirección de Área Territorial. En el caso de que no se reciban en el plazo que se haya indi- cado, se estimará desistida la solicitud de flexibilización.\n5.La Dirección General con competencia en ordenación académica resolverá antes de la finalización de las actividades lectivas, de manera que el alumno pueda anticipar o re- ducir el curso en el año académico siguiente a aquel en el que se ha iniciado el expediente de flexibilización.\nArtículo 19\nRecursos\nLa Dirección General competente en materia de ordenación académica comunicará la resolución a la Dirección de Área Territorial correspondiente para su traslado al Servicio de Inspección Educativa, al centro donde el alumno cursa sus estudios y a los interesados, quienes podrán interponer recurso de alzada contra dicha resolución, ante la Consejería con\ncompetencias en educación, en el plazo de un mes desde el día siguiente a la notificación de la misma.\nArtículo 20\nRegistro de la medida de flexibilización\nLa información relativa a la medida de flexibilización de la duración de las enseñanzas se consignará en los documentos oficiales de evaluación tal como se recoge en el Anexo II.\nArtículo 21\nSeguimiento\n1.El equipo docente y los equipos de orientación educativa y psicopedagógica serán los responsables de valorar la idoneidad de la medida adoptada. Esta se podrá anular cuan- do el alumno no alcance los objetivos propuestos, previo informe de evaluación psicopeda- gógica e informe razonado del equipo docente en el que se recogerá la nueva propuesta, que contará con el consentimiento escrito de los padres o tutores legales.\n2.El Servicio de Inspección Educativa garantizará, mediante informe, que se han respetado el procedimiento y los derechos del alumno.",
            "Sección": [
              {
                "SecciónNumber": 0,
                "SecciónHeader": "",
                "content": "",
                "articles": [
                  {
                    "ArtículoNumber": 15,
                    "ArtículoHeader": "Artículo 15",
                    "content": "1.La flexibilización es una medida de carácter excepcional que consiste en la incor- poración de los alumnos con altas capacidades intelectuales a un curso superior al que por edad le correspondería.\n2.La flexibilización del período de escolarización podrá consistir tanto en la antici- pación del inicio de la Educación Primaria como en la reducción de la duración de esta.",
                    "subtitle": "Definición de flexibilización"
                  },
                  {
                    "ArtículoNumber": 16,
                    "ArtículoHeader": "Artículo 16",
                    "content": "1.La medida de flexibilización para aquellos alumnos con altas capacidades intelec- tuales que tengan un potencial excepcional para el aprendizaje y un elevado rendimiento académico se tomará cuando las medidas educativas que el centro pueda adoptar se consi- deren insuficientes para atender adecuadamente al desarrollo de las capacidades de estos alumnos.\n2.Las decisiones académicas tomadas tras la correspondiente autorización para fle- xibilizar las etapas de Educación Infantil o de Educación Primaria estarán sujetas a un pro- ceso de evaluación. De dichas decisiones se informará a los padres o tutores legales de los alumnos.\n3.El maestro tutor y el equipo docente iniciarán las medidas de ampliación y/o en- riquecimiento curricular una vez detectadas las necesidades del alumno, de acuerdo con lo establecido en el artículo 6 de esta Orden, en tanto se toma la decisión de flexibilización tras la correspondiente evaluación psicopedagógica. La flexibilización se realizará, en su caso, el curso siguiente a aquel en que se haya llevado a cabo la evaluación psicopedagógi- ca del alumno.",
                    "subtitle": "Criterios generales"
                  },
                  {
                    "ArtículoNumber": 17,
                    "ArtículoHeader": "Artículo 17",
                    "content": "1.El inicio de la Educación Primaria podrá anticiparse un año cuando en la evalua- ción psicopedagógica, acreditadas las altas capacidades intelectuales del alumno, se prevea\nque dicha medida es adecuada para su desarrollo intelectual, su equilibrio personal y su so- cialización y que globalmente tiene conseguidos los objetivos de la Educación Infantil.\n2.La Educación Primaria podrá reducirse hasta un máximo de dos cursos cuando en la evaluación psicopedagógica, acreditadas las altas capacidades intelectuales del alumno, se prevea que dicha medida es adecuada para su progreso intelectual y académico, su equi- librio personal y su socialización y que, globalmente, tiene adquiridos los objetivos del cur- so que le correspondería realizar. En el caso de que un alumno haya anticipado el inicio de la Educación Primaria, podrá reducir esta etapa una sola vez.\n3.La Consejería con competencia en materia de educación podrá, en casos excep- cionales, adoptar medidas de flexibilización sin tales limitaciones. Esta flexibilización in- corporará medidas y programas de atención específica.",
                    "subtitle": "Requisitos"
                  },
                  {
                    "ArtículoNumber": 18,
                    "ArtículoHeader": "Artículo 18",
                    "content": "1.El procedimiento para solicitar la flexibilización del período de escolarización será el siguiente:\na)El maestro tutor, una vez detectadas las posibles altas capacidades del alumno in- formará a sus padres o tutores legales de esta circunstancia, a través de la direc- ción del centro y, con su conformidad, solicitará que se realice la evaluación psi- copedagógica del alumno. En este momento se iniciarán medidas de enriquecimiento y/o ampliación del currículo.\nb)La dirección del centro elevará a la Dirección de Área Territorial correspondiente, hasta el 15 de abril incluido de cada año académico, la solicitud de flexibilización, la cual incluirá, en todos los casos, la siguiente documentación:\n—Solicitud de autorización a los padres o tutores legales para realizar la evalua- ción psicopedagógica (Anexo VI).\n—El informe psicopedagógico actualizado, realizado por el equipo de orientación educativa y psicopedagógica. Este informe recogerá, de manera expresa, su propuesta favorable o desfavorable a la solicitud de flexibilización (Anexo I).\n—El informe del equipo docente coordinado por el maestro tutor del alumno. Este informe acreditará que el alumno tiene adquiridos los objetivos del cur- so que va a reducir en el caso de efectuarse la flexibilización (Anexo III).\n—La conformidad expresa de los padres o tutores legales del alumno, con la propuesta (Anexo IV).\n2.El Servicio de Inspección Educativa de la Dirección de Área Territorial corres- pondiente comprobará, una vez recibida la documentación, que se ajusta a lo establecido en esta Orden y emitirá el correspondiente informe (Anexo V).\n3.La Dirección de Área Territorial remitirá a la Dirección General con competencia en ordenación académica, en el plazo de diez días, la documentación mencionada en los apartados 1.b) y 2 de este artículo.\n4.La Dirección General con competencia en ordenación académica podrá requerir informes complementarios a la dirección del centro en el que el alumno esté escolarizado si la documentación del expediente está incompleta o no responde a lo regulado en esta Or- den. Estos informes complementarios se enviarán a dicha Dirección General, con copia a la Dirección de Área Territorial. En el caso de que no se reciban en el plazo que se haya indi- cado, se estimará desistida la solicitud de flexibilización.\n5.La Dirección General con competencia en ordenación académica resolverá antes de la finalización de las actividades lectivas, de manera que el alumno pueda anticipar o re- ducir el curso en el año académico siguiente a aquel en el que se ha iniciado el expediente de flexibilización.",
                    "subtitle": "Procedimiento y plazos"
                  },
                  {
                    "ArtículoNumber": 19,
                    "ArtículoHeader": "Artículo 19",
                    "content": "La Dirección General competente en materia de ordenación académica comunicará la resolución a la Dirección de Área Territorial correspondiente para su traslado al Servicio de Inspección Educativa, al centro donde el alumno cursa sus estudios y a los interesados, quienes podrán interponer recurso de alzada contra dicha resolución, ante la Consejería con\ncompetencias en educación, en el plazo de un mes desde el día siguiente a la notificación de la misma.",
                    "subtitle": "Recursos"
                  },
                  {
                    "ArtículoNumber": 20,
                    "ArtículoHeader": "Artículo 20",
                    "content": "La información relativa a la medida de flexibilización de la duración de las enseñanzas se consignará en los documentos oficiales de evaluación tal como se recoge en el Anexo II.",
                    "subtitle": "Registro de la medida de flexibilización"
                  },
                  {
                    "ArtículoNumber": 21,
                    "ArtículoHeader": "Artículo 21",
                    "content": "1.El equipo docente y los equipos de orientación educativa y psicopedagógica serán los responsables de valorar la idoneidad de la medida adoptada. Esta se podrá anular cuan- do el alumno no alcance los objetivos propuestos, previo informe de evaluación psicopeda- gógica e informe razonado del equipo docente en el que se recogerá la nueva propuesta, que contará con el consentimiento escrito de los padres o tutores legales.\n2.El Servicio de Inspección Educativa garantizará, mediante informe, que se han respetado el procedimiento y los derechos del alumno.",
                    "subtitle": "Seguimiento"
                  }
                ]
              }
            ]
          }
        ]
      }
    ],
    "Disposición": [
      {
        "type": "ADICIONAL",
        "title": "DISPOSICIÓN ADICIONAL ÚNICA",
        "subtitle": "Atención a otros alumnos con necesidades educativas específicas",
        "content": "1.Las instrucciones conjuntas de la Dirección General de Educación Infantil y Pri- maria y de la Dirección General de Educación Secundaria, Formación Profesional y Ense- ñanzas de Régimen Especial, de 12 de diciembre de 2014, establecen medidas para la eva- luación de los alumnos con dislexia, otras dificultades específicas de aprendizaje o trastorno por déficit de atención e hiperactividad (TDAH), en las enseñanzas que recoge la presente Orden.\n2.La evaluación de los alumnos con incorporación tardía al sistema educativo se re- girá por la misma normativa que la de los alumnos del curso al que se hayan incorporado.\n\n\n\n\nDerogación normativa\n"
      },
      {
        "type": "DEROGATORIA",
        "title": "DISPOSICIÓN DEROGATORIA ÚNICA",
        "subtitle": "Quedan derogadas las demás normas de igual o inferior rango que se opongan a lo es- tablecido en la presente Orden.",
        "content": "Quedan derogados los aspectos relativos a los alumnos que cursan las etapas de Edu- cación Infantil y de Educación Primaria regulados en la Orden 70/2005, de 11 de enero, del Consejero de Educación de la Comunidad de Madrid, por la que se regula con carácter ex- cepcional la flexibilización de la duración de las diferentes enseñanzas escolares para los alumnos con necesidades educativas específicas por superdotación intelectual."
      },
      {
        "type": "FINALE",
        "DisposiciónHeader": "Primera",
        "content": "La Dirección General competente en materia de ordenación académica dictará cuan- tas medidas sean precisas para la ejecución de lo establecido en esta Orden y podrá deter- minar las condiciones, medidas y programas que los centros deben ofrecer a los alumnos con altas capacidades intelectuales para prestar una adecuada atención educativa a estos alumnos. Asimismo, dictará los criterios para que los centros elaboren programas específi- cos de enriquecimiento y/o ampliación curricular y las medidas oportunas para que los pa- dres o tutores legales reciban el adecuado asesoramiento sobre las medidas ordinarias o ex- traordinarias de atención educativa que se adopten.",
        "subtitle": "Habilitación"
      },
      {
        "type": "FINALE",
        "DisposiciónHeader": "Segunda",
        "content": "La Consejería con competencia en materia de educación promoverá la realización de cursos de formación específica para los maestros que atiendan a los alumnos con altas ca- pacidades intelectuales.",
        "subtitle": "Formación"
      },
      {
        "type": "FINALE",
        "DisposiciónHeader": "Tercera",
        "content": "Esta Orden entrará en vigor el día siguiente al de su publicación en el BOLETÍN OFI- CIAL DE LA COMUNIDAD DE MADRID.",
        "subtitle": "Entrada en vigor"
      }
    ],
    "Anexo": {
      "Tablas": [
        {
          "TablaHeader": "",
          "content": ""
        }
      ],
      "structural_elements": [
        {
          "structural_elementtHeader": "ANEXO I\nINFORME PSICOPEDAGÓGICO",
          "rawContent": "Datos personales del alumno/a\nApellidos: Nombre:\nDNI/NIE/Pasaporte: Sexo: H M\nFecha de nacimiento: Lugar de nacimiento:\nProvincia: País: Nacionalidad:\nDomicilio: Localidad: C.P.:\nProvincia: Teléfono: Correo electrónico:\nNombre del padre o tutor legal:\nDNI/NIE/Pasaporte: Teléfono de contacto:\nNombre de la madre o tutora legal:\nDNI/NIE/Pasaporte: Teléfono de contacto:\nDatos del Equipo de Orientación Educativa y Psicopedagógica\nSector:\nDirección: Localidad:\nC.P.: Teléfono: Fax: Correo electrónico: Página web:\nDatos actuales de escolarización\nCentro: Código de centro:\nPúblico Dirección: Localidad:\nPrivado C.P.: Teléfono: Correo electrónico:\nEtapa educativa: Curso: Modalidad educativa:\nDatos del informe\nMotivo: ______________________________________________ Fecha de elaboración: ___________\nProfesionales que han intervenido:\n-\n-\n-\nNOTA: Los datos contenidos en este informe son confidenciales. Expresan la situación actual del alumno/a y no presuponen su\nevolución futura. Los profesionales que, en razón de su cargo, deban conocer el contenido de este informe garantizarán su\nCONFIDENCIALIDAD.\nLos datos personales recogidos serán incorporados y tratados en el fichero _______________________, cuya finalidad es el registro y\ngestión de los datos personales, familiares y académicos de los alumnos y ex alumnos de los centros docentes no universitarios de la\nComunidad de Madrid. Inscrito en el Registro de ficheros de datos personales de la Agencia Española de Protección de Datos (www.ag\npd.es). Los datos sólo podrán ser cedidos cuando resulte necesario para la tramitación del expediente. También podrán realizarse\ncesiones a los Tribunales, al Defensor del Pueblo y otras previstas en la Ley. El órgano responsable del fichero es\n___________________________________, Consejería de Educación, Juventud y Deporte de la Comunidad de Madrid en cuya\ndirección el interesado podrá ejercer los derechos de acceso, rectificación, cancelación y oposición mediante solicitud dirigida al mismo\n(________________________________), todo lo cual se informa en cumplimiento del artículo 5 de la Ley Orgánica 15/1999, de 13 de\ndiciembre, de Protección de Datos de Carácter Personal. \nInformación relativa al historial personal y escolar\nAntecedentes y datos relevantes de la evolución\nAspectos biológicos:\nAspectos psicológicos (desarrollo evolutivo):\nAspectos sociofamiliares:\nInformación sobre la historia escolar\nCurso\nacadémico\nCentro\neducativo\nNivel/curso\nrealizado Modalidad educativa Medidas curriculares\nadoptadas (*)\n\n\n\n\n(*) Adaptaciones curriculares significativas y medidas de apoyo. Medidas de enriquecimiento y/o ampliación curricular. Flexibilización.\nApoyos escolares recibidos dentro y fuera de los centros escolares\nOtros apoyos\n(tratamientos, etc.)\nValoración funcional actual de aspectos psicopedagógicos\nTécnicas y pruebas utilizadas\n(con datos cuantitativos y cualitativos)\nDesarrollo biológico, cognitivo, motor y comunicativo-lingüístico\nDesarrollo social y adaptativo tanto en el contexto escolar como en el ámbito familiar\n(conducta, participación en actividades extraescolares...)\nDesarrollo emocional\nNivel de competencia curricular en las distintas áreas\nEstilos de aprendizaje, creatividad, motivaciones, intereses, perseverancia en la tarea...\nInformación relativa a los contextos de desarrollo\nInformación de los contextos\nInformación del contexto escolar:\nInformación del contexto familiar:\nInformación del contexto social:\nDeterminación de las necesidades educativas que manifiesta el alumno/a\nDescripción de las mismas \nCONCLUSIONES\nSíntesis de la evaluación psicopedagógica, propuestas de medidas específicas (adaptaciones\ncurriculares significativas y medidas de apoyo, medidas de enriquecimiento y/o ampliación\ncurricular, flexibilización), recursos materiales y personales necesarios y modalidad educativa\nrecomendada\nModalidad educativa recomendada:\nEn ________________________, a _____ de ________________ de 20____\nFdo.: ________________________ Fdo.: ________________________ Fdo.: _______________________\n(Nombre y firma de los profesionales que han intervenido)\nVº Bº\nEl/la director/a del centro o director/a del E.O.E.P. \nANEXO AL INFORME PSICOPEDAGÓGICO\nNIA:\nDatos personales del alumno/a\nApellidos: Nombre:\nDNI/NIE/Pasaporte: Sexo: H M\nFecha de nacimiento: Lugar de nacimiento:\nProvincia: País: Nacionalidad:\nDatos actuales de escolarización\nCentro: Código de centro:\nPúblico Dirección: Localidad:\nPrivado C.P.: Teléfono: Correo electrónico:\nEtapa educativa: Curso: Modalidad educativa:\nDatos del Equipo de Orientación Educativa y Psicopedagógica\nSector:\nDirección: Localidad:\nC.P.: Teléfono: Fax: Correo electrónico: Página web:\nORIENTACIONES\nPara el contexto escolar\n(Medidas de personalización de aprendizaje: metodológicas, organizativas...; adaptaciones de acceso, curriculares significativas, de enriquecimiento y/o ampliación curricular y,\nen su caso, de flexibilización del período de escolaridad, recursos materiales y personales necesarios y modalidades de apoyo)\nPara el contexto familiar\nEn ________________________, a _____ de ________________ de 20____\nFdo.: _______________________________ Fdo.: _______________________________ Fdo.: ______________________________\n(Nombre y firma de los profesionales que han intervenido)\nVº Bº\nEl/la director/a del centro o director/a del E.O.E.P.\n(sello del E.O.E.P. o del centro)\nFdo.: ____________________________________________",
          "page": 10
        },
        {
          "structural_elementtHeader": "ANEXO II\nREGISTRO DE LAS ADAPTACIONES CURRICULARES SIGNIFICATIVAS Y DE LA MEDIDA DE FLEXIBILIZACIÓN EN LOS DOCUMENTOS DE EVALUACIÓN",
          "rawContent": "1.EDUCACIÓN INFANTIL\n\na)En el expediente personal del alumno, en los siguientes apartados:\n\n-Datos médicos y psicopedagógicos relevantes.\n\n-Medidas de atención a la diversidad: medidas de apoyo específico para alumnos con\n \nnecesidades\n \neducativas\n \nespecialesyáreascon\n \nadaptacionescurriculares\n \nsignificativas y\n \ndescripción de las\n \nmismas. Medidas de apoyo específico para los\n \nalumnos con altas capacidades intelectuales.\n\n \nb)En el informe final de aprendizaje se cumplimentará lo que apartados:\n \nproceda en los\n \n\n-Situación del alumno.\n\n-Medidas de apoyo adoptadas.\n\n-Observaciones.\n\nEl grado de consecución de los objetivos en las áreas del segundo ciclo de Educación\n \nInfantil se consignará con las siglas C, NC, proceso) como para el resto de los alumnos.\n \nEP (conseguido, no\n \nconseguido, en\n \n\nc)En la certificación para el traslado, en el apartado 'Observaciones'.\n\n2.EDUCACIÓN PRIMARIA\n\nEn  la  Educación  Primaria  las  adaptaciones  curriculares  significativas  y  las\ncalificaciones obtenidas por el alumno y la medida de flexibilización se consignarán en los siguientes documentos oficiales de evaluación:\n\n \na)En el expediente académico y siguientes apartados:\n \nen el his orial académico del\n \nalumno en los\n \n\n- Medidas de atención a la diversidad: medidas de apoyo específico para alumnos con\n \nnecesidades\n \neducativas\n \nespecialesyáreascon\n \nadaptacionescurriculares\n \nsignificativas y\n \ndescripción de las\n \nmismas. Medidas de apoyo específico para los\n \nalumnos con altas capacidades intelectuales.\n\n-Datos médicos y psicopedagógicos relevantes.\n\n-Evaluación: Resultados de la evaluación de los distintos cursos de la Educación\n \nPrimaria, en la\n \ncolumna\n \n'MA' de\n \nlas correspondientes\n \náreas, como 'Adaptación\n \nCurricular Significativa' expresada con el término (AC). Este término (AC) se utilizará exclusivamente para las adaptaciones curriculares significativas de los alumnos que tras la evaluación psicopedagógica, presenten necesidades educativas especiales.\nb)En las actas de evaluación finales, dentro del apartado 'Calificaciones obtenidas por los alumnos en las distintas áreas', en la columna 'MA como 'Adaptación Curricular Significativa', expresada con el término (AC).\n\nc)En el informe personal por traslado, en la columna 'MA' y en el apartado Observaciones.\n\nd)En el informe final de etapa, en los apartados: en la columna 'MA' de las correspondientes áreas, como 'Adaptación Curricular Significativa' expresada con el término (AC) y en el apartado “Situación del alumno”.\n\ne)En la certificación académica completa por traslado al extranjero, en el apartado 'Resultados de la evaluación de los distintos cursos de la etapa', en la columna Medidas adoptadas, como adaptación curricular significativa expresada con el término AC y en el apartado 'Diligencias y observaciones'.\n\nLa información relativa a la adaptación curricular significativa indicará el nivel al que corresponde dicha adaptación, en el expediente académico y en el historial académico en el apartado áreas con adaptaciones curriculares significativas y descripción de las mismas y en el informe final de etapa en el apartado observaciones.\n\nLa nota de la adaptación curricular significativa hará referencia al curso al cual pertenece dicha adaptación y no necesariamente al curso en el que el alumno esté matriculado.\n\n3.ENSEÑANZA BÁSICA OBLIGATORIA\n\nEn la Enseñanza Básica Obligatoria, la información relativa a las adaptaciones curriculares significativas se consignará en los documentos oficiales de evaluación establecidos en los apartados que correspondan en los siguientes documentos:\n\na)En el expediente académico del alumno.\n\nb)En el historial académico de Enseñanza Básica Obligatoria.\n\nc)En las actas de evaluación final.\n\nd)En el informe personal por traslado.\n\ne)En el informe final de la Enseñanza Básica Obligatoria.",
          "page": 16
        },
        {
          "structural_elementtHeader": "ANEXO III\nINFORME DEL EQUIPO DOCENTE COORDINADO POR EL MAESTRO/A TUTOR/A",
          "rawContent": "Datos personales del alumno/a\nApellidos: Nombre:\nDNI/NIE/Pasaporte: Sexo: H M\nFecha de nacimiento: Lugar de nacimiento:\nProvincia: País: Nacionalidad:\nDomicilio: Localidad: C.P.:\nProvincia: Teléfono: Correo electrónico:\nNombre del padre o tutor legal:\nDNI/NIE/Pasaporte: Teléfono de contacto:\nNombre de la madre o tutora legal:\nDNI/NIE/Pasaporte: Teléfono de contacto:\nDatos escolares del alumno\nCurso:\nTutor/a:\nDatos del centro\nCentro: Código de centro:\nPúblico Dirección: Localidad:\nPrivado C.P.: Teléfono: Correo electrónico:\nINFORMACIÓN APORTADA POR EL MAESTRO/A TUTOR/A Y\nEL EQUIPO DOCENTE DEL ALUMNO/A\nAspectos valorables\nCompetencia curricular\nNivel de competencia curricular en cada una de las áreas. Especificar cada una de ellas:\nDatos relevantes de su evolución académica:\nDatos relevantes sobre el desarrollo general y social del alumno/a y sobre su madurez personal y\ndesarrollo social\nDesarrollo biológico, intelectual, motor y comunicativo-lingüístico:\nDatos relevantes sobre su madurez personal:\nInserción social en el centro y en la familia: (antecedentes y expectativas; relación con los/las compañeros/as, los/las\nmaestros/as y otros adultos)\nOtras informaciones significativas\n(intereses, motivaciones)\nMedidas educativas adoptadas con el alumno/a durante el presente curso y cursos anteriores\n(especificar las áreas en las que se ha realizado)\nAdaptaciones curriculares significativas: (para alumnos/as con necesidades educativas especiales)\nMedidas de enriquecimiento curricular y/o ampliación: (para alumnos/as con altas capacidades)\nOtras: (especificar)\nCONCLUSIONES\nEl equipo docente del alumno/a ___________________________________________, que cursa\n____________________ (nivel/etapa), durante el año académico 20___ / 20___, acredita que, después de\nla evaluación correspondiente, dicho alumno/a:\nDebe permanecer un año más en el segundo ciclo de Educación Infantil\nDebe permanecer un año más en el último curso de Educación Primaria\nPrecisa medidas de enriquecimiento y/o ampliación curricular\nTiene adquiridos los objetivos del curso superior al que, por edad, le corresponde y posee la madurez\ncognitiva, emocional y social para integrarse en un grupo de alumnos mayores en edad. Por ello, se\nconsidera que la flexibilización es una medida adecuada para dar respuesta a sus necesidades\neducativas específicas.\nObservaciones\nEn ________________________, a _____ de ________________ de 20____\n Vº Bº\nEl/la director/a del centro El tutor/a\n(sello del centro)\nFdo.: _________________________________ Fdo.: _________________________________\nFIRMA DEL EQUIPO DOCENTE\nÁrea:______________________________\nFdo.:______________________________\nÁrea:______________________________\nFdo.:______________________________\nÁrea:______________________________\nFdo.:______________________________\nÁrea:______________________________\nFdo.:______________________________\nÁrea:______________________________\nFdo.:______________________________\nÁrea:______________________________\nFdo.:______________________________",
          "page": 18
        },
        {
          "structural_elementtHeader": "ANEXO IV\nCONFORMIDAD DE LOS PADRES/TUTORES LEGALES CON LA PROPUESTA",
          "rawContent": "D. ________________________________________________________________________ y\nDña. _______________________________________________________________________,\ncomo padres/tutores legales del alumno/a _________________________________________,\ncon domicilio en la localidad de _______________________________________________,\ncalle _____________________________________________, número _____, C.P. _________\ny teléfonos de contacto _______________________________________________________,\nEXPONEN\nQue, habiendo sido informados por el centro _________________________________ (nombre\ndel centro) de la propuesta de:\nPermanencia un año más en Educación Infantil\nEnriquecimiento y/o ampliación curricular\nFlexibilización de las enseñanzas de Educación __________________________ (etapa),\ncursando ________________________________________ (nivel/etapa) en lugar de\n________________________________________ (nivel/etapa), como medida adecuada\npara el desarrollo de su equilibrio personal y de su socialización, para el año académico\n20___ /20___\n________________________________________________________________\nMANIFIESTAN\nSu conformidad con la propuesta\n____________, a ____ de ________________ de _______\nEl padre o tutor legal La madre o tutora legal\n\nFdo.: ___________________________ Fdo.: ______________________",
          "page": 21
        },
        {
          "structural_elementtHeader": "ANEXO V\nINFORME DEL SERVICIO DE INSPECCIÓN EDUCATIVA",
          "rawContent": "D./Dª.___________________________________________________________, Inspector/a de\neducación de la Dirección de Área Territorial de Madrid ________________, en relación con la\nsolicitud de:\nPermanencia un año más en el segundo ciclo de Educación Infantil\nPermanencia un año más en el último curso de Educación Primaria\nMedidas de enriquecimiento y/o ampliación curricular\nFlexibilización del período de escolarización\n_________________________________________________________________________\ndel alumno/a _____________________________________________________, remitida por el\ncentro ___________________________________________________________________, de\n___________________________________, de Madrid, que contiene:\nInforme del equipo docente.\nInforme psicopedagógico realizado por el EOEP/Orientador de _____________, en el que\nconsta que:\n El alumno/a tiene necesidades específicas\n La medida propuesta es la más adecuada para responder a las necesidades\neducativas específicas que presenta\nConformidad de los padres o tutores legales del alumno/a con la medida\nConsiderando, además, que:\nLa solicitud SI/NO se ajusta en fondo y forma a lo establecido en la Orden de la Consejería\ncompetente en materia de ordenación académica por la que se regula la evaluación y la\npromoción de los alumnos con necesidad específica de apoyo educativo, que cursen\nsegundo ciclo de Educación Infantil, Educación Primaria y Enseñanza Básica Obligatoria,\nasí como la flexibilización de la duración de las enseñanzas de los alumnos con altas\ncapacidades intelectuales.\nLos derechos del alumno/a y de su familia han sido respetados.\nOtras consideraciones: ______________________________________________________\n_________________________________________________________________________\nInforma FAVORABLE/DESFAVORABLEMENTE la propuesta para que dicho alumno/a, en el\naño académico 20___/20___, se escolarice en el ________ curso de Educación\n_________________________.\n____________, a ___ de ________________ de 20____\n VºBº\nEl Jeje/a del Servicio de Inspección/Distrito El Inspector/a de educación\nFdo.: __________________________ Fdo.: _______________________",
          "page": 22
        },
        {
          "structural_elementtHeader": "ANEXO VI\nAUTORIZACIÓN DE LOS PADRES/TUTORES LEGALES PARA LA REALIZACIÓN DE LA\nEVALUACIÓN PSICOPEDAGÓGICA",
          "rawContent": "D. ________________________________________, DNI/NIE/Pasaporte _______________ y\nDña. _____________________________________, DNI/NIE/Pasaporte _________________,\ncomo padres/tutores legales del alumno ___________________________________________,\nescolarizado en el centro público/privado ______________________________________,\ncódigo __________, dirección ___________________________, localidad _______________,\ny con domicilio, a efectos de notificación, en la localidad de _________________________,\ncalle ___________________________________________, número _______, C.P. _________\ny teléfonos de contacto ________________________________________________________\nAUTORIZAN\nLa realización de la evaluación psicopedagógica de su hijo/a a fin de determinar, en su caso,\nlas necesidades específicas de apoyo educativo así como la respuesta educativa más\nadecuada a las mismas.\n____________, a ___ de ________________ de _______\nEl padre o tutor legal La madre o tutora legal\n\nFdo.: _________________________ Fdo.: _______________________",
          "page": 23
        }
      ]
    }
  }
}
